{
    "AX": {
        "error": 0.00513322448913194, 
        "filter_outliers_dict": {
            "filter_outliers": true, 
            "iterations": 1, 
            "std_devs": 2
        }, 
        "fit": "average", 
        "value": 0.040309881965682776
    }, 
    "CDD": {
        "error": 3.4328038065308233e-06, 
        "filter_outliers_dict": {
            "filter_outliers": true, 
            "iterations": 1, 
            "std_devs": 10
        }, 
        "fit": "average", 
        "value": 1.0008256930161533e-05
    }, 
    "H1": {
        "error": 0.002748526917165132, 
        "filter_outliers_dict": {
            "filter_outliers": true, 
            "iterations": 1, 
            "std_devs": 2
        }, 
        "fit": "average", 
        "value": -0.03722775338948615
    }, 
    "H2": {
        "error": 0.004658335223318149, 
        "filter_outliers_dict": {
            "filter_outliers": true, 
            "iterations": 1, 
            "std_devs": 2
        }, 
        "fit": "average", 
        "value": 0.07104443131828701
    }, 
    "L1": {
        "error": 0.0019254804418838865, 
        "filter_outliers_dict": {
            "filter_outliers": true, 
            "iterations": 1, 
            "std_devs": 2
        }, 
        "fit": "average", 
        "value": -0.023698922854487596
    }, 
    "L2": {
        "error": 0.0038376890745296316, 
        "filter_outliers_dict": {
            "filter_outliers": true, 
            "iterations": 1, 
            "std_devs": 2
        }, 
        "fit": "average", 
        "value": 0.14037570606869346
    }
}