{
    "AX": {
        "error": 0.00437152635752233, 
        "filter_outliers_dict": {
            "filter_outliers": true, 
            "iterations": 1, 
            "std_devs": 2
        }, 
        "fit": "average", 
        "value": 0.01952913127746253
    }, 
    "CDD": {
        "error": 1.7704677767196888e-06, 
        "filter_outliers_dict": {
            "filter_outliers": true, 
            "iterations": 1, 
            "std_devs": 10
        }, 
        "fit": "average", 
        "value": 2.5144065636084837e-06
    }, 
    "H1": {
        "error": 0.0035631116233769463, 
        "filter_outliers_dict": {
            "filter_outliers": true, 
            "iterations": 1, 
            "std_devs": 2
        }, 
        "fit": "average", 
        "value": -0.044419069867934265
    }, 
    "H2": {
        "error": 0.00472244490567017, 
        "filter_outliers_dict": {
            "filter_outliers": true, 
            "iterations": 1, 
            "std_devs": 2
        }, 
        "fit": "average", 
        "value": 0.06630379317636724
    }, 
    "L1": {
        "error": 0.0017323900009572294, 
        "filter_outliers_dict": {
            "filter_outliers": true, 
            "iterations": 1, 
            "std_devs": 2
        }, 
        "fit": "average", 
        "value": -0.0028302049089211304
    }, 
    "L2": {
        "error": 0.004431270306942596, 
        "filter_outliers_dict": {
            "filter_outliers": true, 
            "iterations": 1, 
            "std_devs": 2
        }, 
        "fit": "average", 
        "value": 0.1277837992912198
    }
}