{
    "AX": {
        "error": 0.004086237980474106, 
        "filter_outliers_dict": {
            "filter_outliers": true, 
            "iterations": 1, 
            "std_devs": 2
        }, 
        "fit": "average", 
        "value": 0.04239647290698059
    }, 
    "CDD": {
        "error": 2.4703242891869865e-06, 
        "filter_outliers_dict": {
            "filter_outliers": true, 
            "iterations": 1, 
            "std_devs": 10
        }, 
        "fit": "average", 
        "value": 5.004128465080767e-06
    }, 
    "H1": {
        "error": 0.003563687876321062, 
        "filter_outliers_dict": {
            "filter_outliers": true, 
            "iterations": 1, 
            "std_devs": 2
        }, 
        "fit": "average", 
        "value": -0.04160297878145033
    }, 
    "H2": {
        "error": 0.004796809626613956, 
        "filter_outliers_dict": {
            "filter_outliers": true, 
            "iterations": 1, 
            "std_devs": 2
        }, 
        "fit": "average", 
        "value": 0.06899693694897693
    }, 
    "L1": {
        "error": 0.0017450944478784602, 
        "filter_outliers_dict": {
            "filter_outliers": true, 
            "iterations": 1, 
            "std_devs": 2
        }, 
        "fit": "average", 
        "value": -0.009145549654015655
    }, 
    "L2": {
        "error": 0.0033045262854704406, 
        "filter_outliers_dict": {
            "filter_outliers": true, 
            "iterations": 1, 
            "std_devs": 2
        }, 
        "fit": "average", 
        "value": 0.11067316318654323
    }
}