{
    "AX": {
        "error": 0.007561392773045885, 
        "filter_outliers_dict": {
            "filter_outliers": true, 
            "iterations": 1, 
            "std_devs": 2
        }, 
        "fit": "average", 
        "value": 0.024616311788874464
    }, 
    "CDD": {
        "error": 3.0024770790484588e-06, 
        "filter_outliers_dict": {
            "filter_outliers": true, 
            "iterations": 1, 
            "std_devs": 10
        }, 
        "fit": "average", 
        "value": 3.0024770790484596e-06
    }, 
    "H1": {
        "error": 0.005736684017459232, 
        "filter_outliers_dict": {
            "filter_outliers": true, 
            "iterations": 1, 
            "std_devs": 2
        }, 
        "fit": "average", 
        "value": -0.044513773559162285
    }, 
    "H2": {
        "error": 0.0046918369169259115, 
        "filter_outliers_dict": {
            "filter_outliers": true, 
            "iterations": 1, 
            "std_devs": 2
        }, 
        "fit": "average", 
        "value": 0.08080937555332394
    }, 
    "L1": {
        "error": 0.0019069631297136977, 
        "filter_outliers_dict": {
            "filter_outliers": true, 
            "iterations": 1, 
            "std_devs": 2
        }, 
        "fit": "average", 
        "value": -0.0037569667697792256
    }, 
    "L2": {
        "error": 0.0067184412330792646, 
        "filter_outliers_dict": {
            "filter_outliers": true, 
            "iterations": 1, 
            "std_devs": 2
        }, 
        "fit": "average", 
        "value": 0.13121873704331644
    }
}