{
    "AX": {
        "error": 0.004870363290643159, 
        "filter_outliers_dict": {
            "filter_outliers": true, 
            "iterations": 1, 
            "std_devs": 2
        }, 
        "fit": "average", 
        "value": 0.027837713203723045
    }, 
    "CDD": {
        "error": 3.2413077459847006e-06, 
        "filter_outliers_dict": {
            "filter_outliers": true, 
            "iterations": 1, 
            "std_devs": 10
        }, 
        "fit": "average", 
        "value": 8.800422972629691e-06
    }, 
    "H1": {
        "error": 0.0036831142024283396, 
        "filter_outliers_dict": {
            "filter_outliers": true, 
            "iterations": 1, 
            "std_devs": 2
        }, 
        "fit": "average", 
        "value": -0.041850831035499025
    }, 
    "H2": {
        "error": 0.00448295375374695, 
        "filter_outliers_dict": {
            "filter_outliers": true, 
            "iterations": 1, 
            "std_devs": 2
        }, 
        "fit": "average", 
        "value": 0.08702189955949965
    }, 
    "L1": {
        "error": 0.0017931537077201113, 
        "filter_outliers_dict": {
            "filter_outliers": true, 
            "iterations": 1, 
            "std_devs": 2
        }, 
        "fit": "average", 
        "value": -0.0022982192976016614
    }, 
    "L2": {
        "error": 0.003761103793545478, 
        "filter_outliers_dict": {
            "filter_outliers": true, 
            "iterations": 1, 
            "std_devs": 2
        }, 
        "fit": "average", 
        "value": 0.13147168864476044
    }
}