{
    "AX": {
        "error": 0.005302293252766011, 
        "filter_outliers_dict": {
            "filter_outliers": true, 
            "iterations": 1, 
            "std_devs": 2
        }, 
        "fit": "average", 
        "value": 0.035355768147282425
    }, 
    "CDD": {
        "error": 3.803569190157381e-06, 
        "filter_outliers_dict": {
            "filter_outliers": true, 
            "iterations": 1, 
            "std_devs": 10
        }, 
        "fit": "average", 
        "value": 1.2510321162701914e-05
    }, 
    "H1": {
        "error": 0.0029469442150726944, 
        "filter_outliers_dict": {
            "filter_outliers": true, 
            "iterations": 1, 
            "std_devs": 2
        }, 
        "fit": "average", 
        "value": -0.03639777703892113
    }, 
    "H2": {
        "error": 0.004537572093228155, 
        "filter_outliers_dict": {
            "filter_outliers": true, 
            "iterations": 1, 
            "std_devs": 2
        }, 
        "fit": "average", 
        "value": 0.061875509143715264
    }, 
    "L1": {
        "error": 0.001819326746742078, 
        "filter_outliers_dict": {
            "filter_outliers": true, 
            "iterations": 1, 
            "std_devs": 2
        }, 
        "fit": "average", 
        "value": -0.0020412532664364244
    }, 
    "L2": {
        "error": 0.003909847964242014, 
        "filter_outliers_dict": {
            "filter_outliers": true, 
            "iterations": 1, 
            "std_devs": 2
        }, 
        "fit": "average", 
        "value": 0.119947080800761
    }
}