{
    "AX": {
        "error": 0.0041668898563469135, 
        "filter_outliers_dict": {
            "filter_outliers": true, 
            "iterations": 1, 
            "std_devs": 2
        }, 
        "fit": "average", 
        "value": 0.025518765686826626
    }, 
    "CDD": {
        "error": 2.1485651963142924e-06, 
        "filter_outliers_dict": {
            "filter_outliers": true, 
            "iterations": 1, 
            "std_devs": 10
        }, 
        "fit": "average", 
        "value": 3.7530963488105745e-06
    }, 
    "H1": {
        "error": 0.004023023451786286, 
        "filter_outliers_dict": {
            "filter_outliers": true, 
            "iterations": 1, 
            "std_devs": 2
        }, 
        "fit": "average", 
        "value": -0.04296866629454695
    }, 
    "H2": {
        "error": 0.0036756717029995194, 
        "filter_outliers_dict": {
            "filter_outliers": true, 
            "iterations": 1, 
            "std_devs": 2
        }, 
        "fit": "average", 
        "value": 0.06801554347747214
    }, 
    "L1": {
        "error": 0.0018197523740439117, 
        "filter_outliers_dict": {
            "filter_outliers": true, 
            "iterations": 1, 
            "std_devs": 2
        }, 
        "fit": "average", 
        "value": -0.003170347746583423
    }, 
    "L2": {
        "error": 0.0036319050976619223, 
        "filter_outliers_dict": {
            "filter_outliers": true, 
            "iterations": 1, 
            "std_devs": 2
        }, 
        "fit": "average", 
        "value": 0.13213588835552428
    }
}