{
    "Ar36": {
        "error": 0.00012946488103959412, 
        "filter_outliers_dict": {
            "filter_outliers": true, 
            "iterations": 1, 
            "std_devs": 2
        }, 
        "fit": "Parabolic", 
        "value": 0.002892487564133206
    }, 
    "Ar37": {
        "error": 0.005007470694928083, 
        "filter_outliers_dict": {
            "filter_outliers": true, 
            "iterations": 1, 
            "std_devs": 2
        }, 
        "fit": "linear", 
        "value": 0.1436812837783198
    }, 
    "Ar38": {
        "error": 0.0022366583505292505, 
        "filter_outliers_dict": {
            "filter_outliers": true, 
            "iterations": 1, 
            "std_devs": 2
        }, 
        "fit": "linear", 
        "value": -0.005256154713625269
    }, 
    "Ar39": {
        "error": 0.009040323378575212, 
        "filter_outliers_dict": {
            "filter_outliers": true, 
            "iterations": 1, 
            "std_devs": 2
        }, 
        "fit": "Parabolic", 
        "value": 0.056381355041797414
    }, 
    "Ar40": {
        "error": 0.0070706554099954945, 
        "filter_outliers_dict": {
            "filter_outliers": true, 
            "iterations": 1, 
            "std_devs": 2
        }, 
        "fit": "Parabolic", 
        "value": 0.6812466641161707
    }, 
    "Ar41": {
        "error": 0.004985934809503815, 
        "filter_outliers_dict": {
            "filter_outliers": true, 
            "iterations": 1, 
            "std_devs": 2
        }, 
        "fit": "linear", 
        "value": 0.07116739370466127
    }
}